MANIFEST.in
NEWS.txt
README.rst
setup.py
src/iscool_e/__init__.py
src/iscool_e.bellman.egg-info/PKG-INFO
src/iscool_e.bellman.egg-info/SOURCES.txt
src/iscool_e.bellman.egg-info/dependency_links.txt
src/iscool_e.bellman.egg-info/namespace_packages.txt
src/iscool_e.bellman.egg-info/not-zip-safe
src/iscool_e.bellman.egg-info/requires.txt
src/iscool_e.bellman.egg-info/top_level.txt
src/iscool_e/bellman/__init__.py
src/iscool_e/bellman/pushd.py