Metadata-Version: 1.1
Name: iscool-e.bellman
Version: 0.4
Summary: A library to support the REST API ofmobile push notification server Pushd
Home-page: https://github.com/IsCoolEntertainment/bellman-sdk
Author: Thomas Ferreira
Author-email: thomas.ferreira@iscool-e.com
License: MIT
Keywords: pushd sdk api python
Platform: UNKNOWN
Classifier: Development Status :: 4 - Beta
Classifier: Intended Audience :: Developers
Classifier: Intended Audience :: Information Technology
Classifier: License :: OSI Approved :: MIT License
Classifier: Operating System :: OS Independent
Classifier: Programming Language :: Python
Classifier: Programming Language :: Python :: 2.6
Classifier: Programming Language :: Python :: 2.7
Classifier: Topic :: Internet :: WWW/HTTP
Classifier: Topic :: Software Development :: Libraries
Classifier: Topic :: Software Development :: Libraries :: Python Modules
Classifier: Topic :: Utilities
